{"version":2,"droids":[{"template":"ConstructionDroid","id":37,"position":[2880,1472],"rotation":0,"startpos":0},{"template":"ConstructionDroid","id":38,"position":[3008,1472],"rotation":0,"startpos":0},{"template":"ConstructionDroid","id":39,"position":[3136,1472],"rotation":0,"startpos":0},{"template":"ConstructionDroid","id":40,"position":[3264,1472],"rotation":0,"startpos":0},{"template":"ConstructionDroid","id":152,"position":[1472,13760],"rotation":0,"startpos":3},{"template":"ConstructionDroid","id":153,"position":[1472,13632],"rotation":0,"startpos":3},{"template":"ConstructionDroid","id":154,"position":[1472,13504],"rotation":0,"startpos":3},{"template":"ConstructionDroid","id":155,"position":[1472,13376],"rotation":0,"startpos":3},{"template":"ConstructionDroid","id":156,"position":[13760,15168],"rotation":0,"startpos":2},{"template":"ConstructionDroid","id":157,"position":[13632,15168],"rotation":0,"startpos":2},{"template":"ConstructionDroid","id":158,"position":[13504,15168],"rotation":0,"startpos":2},{"template":"ConstructionDroid","id":159,"position":[13376,15168],"rotation":0,"startpos":2},{"template":"ConstructionDroid","id":160,"position":[15168,2880],"rotation":0,"startpos":1},{"template":"ConstructionDroid","id":161,"position":[15168,3008],"rotation":0,"startpos":1},{"template":"ConstructionDroid","id":162,"position":[15168,3136],"rotation":0,"startpos":1},{"template":"ConstructionDroid","id":163,"position":[15168,3264],"rotation":0,"startpos":1}]}