{"version":2,"droids":[{"template":"BaBaPeople","id":300,"position":[16448,13888],"rotation":0,"player":"scavenger"},{"template":"ConstructionDroid","id":258,"position":[28864,2112],"rotation":0,"startpos":2},{"template":"BaBaPeople","id":106,"position":[16192,9152],"rotation":0,"player":"scavenger"},{"template":"BaBaPeople","id":107,"position":[16320,9280],"rotation":0,"player":"scavenger"},{"template":"BaBaPeople","id":108,"position":[16320,9024],"rotation":43508,"player":"scavenger"},{"template":"BaBaPeople","id":109,"position":[15808,8384],"rotation":42416,"player":"scavenger"},{"template":"BaBaPeople","id":110,"position":[15808,8128],"rotation":0,"player":"scavenger"},{"template":"BaBaPeople","id":111,"position":[16064,8512],"rotation":30947,"player":"scavenger"},{"template":"BaBaPeople","id":112,"position":[16192,8512],"rotation":8738,"player":"scavenger"},{"template":"BaBaPeople","id":113,"position":[16064,8384],"rotation":56433,"player":"scavenger"},{"template":"BaBaPeople","id":114,"position":[17856,8896],"rotation":48969,"player":"scavenger"},{"template":"BaBaPeople","id":115,"position":[17856,9024],"rotation":20571,"player":"scavenger"},{"template":"BaBaPeople","id":116,"position":[17984,9152],"rotation":40049,"player":"scavenger"},{"template":"BaBaPeople","id":117,"position":[17600,8768],"rotation":44054,"player":"scavenger"},{"template":"BaBaPeople","id":118,"position":[17472,8896],"rotation":53339,"player":"scavenger"},{"template":"BaBaPeople","id":119,"position":[17856,8512],"rotation":56615,"player":"scavenger"},{"template":"BaBaPeople","id":120,"position":[17216,8896],"rotation":64625,"player":"scavenger"},{"template":"BaBaPeople","id":121,"position":[16704,8128],"rotation":48787,"player":"scavenger"},{"template":"BaBaPeople","id":122,"position":[16704,8256],"rotation":18204,"player":"scavenger"},{"template":"BaBaPeople","id":123,"position":[16960,8128],"rotation":44964,"player":"scavenger"},{"template":"BabaJeep","id":124,"position":[16448,8896],"rotation":7463,"player":"scavenger"},{"template":"BabaJeep","id":125,"position":[15808,8640],"rotation":52610,"player":"scavenger"},{"template":"BabaJeep","id":126,"position":[17984,8384],"rotation":1274,"player":"scavenger"},{"template":"BabaRKJeep","id":127,"position":[17088,8256],"rotation":62987,"player":"scavenger"},{"template":"BabaFireCan","id":128,"position":[16704,8640],"rotation":2730,"player":"scavenger"},{"template":"BaBaPeople","id":129,"position":[16704,8896],"rotation":2002,"player":"scavenger"},{"template":"BaBaPeople","id":130,"position":[16832,9024],"rotation":35862,"player":"scavenger"},{"template":"BaBaPeople","id":131,"position":[15936,1088],"rotation":64079,"player":"scavenger"},{"template":"BaBaPeople","id":132,"position":[15808,832],"rotation":28945,"player":"scavenger"},{"template":"BaBaPeople","id":133,"position":[15424,704],"rotation":46967,"player":"scavenger"},{"template":"BaBaPeople","id":134,"position":[15424,960],"rotation":4551,"player":"scavenger"},{"template":"BaBaPeople","id":135,"position":[15552,1216],"rotation":60438,"player":"scavenger"},{"template":"BaBaPeople","id":136,"position":[15808,1472],"rotation":21663,"player":"scavenger"},{"template":"BabaJeep","id":137,"position":[15680,1216],"rotation":8738,"player":"scavenger"},{"template":"BaBaPeople","id":138,"position":[15424,20288],"rotation":54067,"player":"scavenger"},{"template":"BaBaPeople","id":139,"position":[15680,20416],"rotation":57708,"player":"scavenger"},{"template":"BaBaPeople","id":140,"position":[15552,19776],"rotation":546,"player":"scavenger"},{"template":"BaBaPeople","id":141,"position":[15680,20032],"rotation":44782,"player":"scavenger"},{"template":"BaBaPeople","id":142,"position":[15552,20288],"rotation":44054,"player":"scavenger"},{"template":"BaBaPeople","id":143,"position":[15168,20160],"rotation":7099,"player":"scavenger"},{"template":"BabaJeep","id":144,"position":[15168,19904],"rotation":18022,"player":"scavenger"},{"template":"ConstructionDroid","id":185,"position":[2752,1600],"rotation":0,"startpos":0},{"template":"ConstructionDroid","id":186,"position":[2496,1984],"rotation":0,"startpos":0},{"template":"ConstructionDroid","id":184,"position":[2752,2624],"rotation":0,"startpos":0},{"template":"ConstructionDroid","id":218,"position":[2496,20672],"rotation":0,"startpos":1},{"template":"ConstructionDroid","id":219,"position":[2240,20800],"rotation":0,"startpos":1},{"template":"ConstructionDroid","id":220,"position":[2624,19776],"rotation":0,"startpos":1},{"template":"ConstructionDroid","id":259,"position":[28480,2112],"rotation":0,"startpos":2},{"template":"ConstructionDroid","id":260,"position":[28096,2752],"rotation":0,"startpos":2},{"template":"ConstructionDroid","id":292,"position":[28224,20160],"rotation":0,"startpos":3},{"template":"ConstructionDroid","id":293,"position":[27968,20416],"rotation":0,"startpos":3},{"template":"ConstructionDroid","id":294,"position":[27072,20288],"rotation":0,"startpos":3},{"template":"BaBaPeople","id":297,"position":[16192,14016],"rotation":0,"player":"scavenger"},{"template":"BabaJeep","id":304,"position":[16448,14272],"rotation":0,"player":"scavenger"},{"template":"BaBaPeople","id":298,"position":[16320,14144],"rotation":0,"player":"scavenger"},{"template":"BabaJeep","id":303,"position":[16064,14272],"rotation":0,"player":"scavenger"},{"template":"BaBaPeople","id":306,"position":[16064,14656],"rotation":0,"player":"scavenger"},{"template":"BaBaPeople","id":302,"position":[16064,14528],"rotation":0,"player":"scavenger"},{"template":"BaBaPeople","id":301,"position":[15936,14528],"rotation":0,"player":"scavenger"},{"template":"BaBaPeople","id":305,"position":[16064,14144],"rotation":0,"player":"scavenger"},{"template":"BabaRKJeep","id":311,"position":[15424,20544],"rotation":31675,"player":"scavenger"},{"template":"BaBaPeople","id":299,"position":[16320,14400],"rotation":0,"player":"scavenger"},{"template":"BaBaPeople","id":310,"position":[15168,20544],"rotation":47149,"player":"scavenger"},{"template":"BaBaPeople","id":309,"position":[15424,19776],"rotation":51882,"player":"scavenger"}]}