{"version":2,"droids":[{"template":"ConstructionDroid","id":526,"position":[11328,11584],"rotation":0,"startpos":3},{"template":"ConstructionDroid","id":525,"position":[11328,11712],"rotation":0,"startpos":3},{"template":"ConstructionDroid","id":528,"position":[11712,11328],"rotation":0,"startpos":3},{"template":"ConstructionDroid","id":527,"position":[11584,11328],"rotation":0,"startpos":3},{"template":"ConstructionDroid","id":418,"position":[1088,1472],"rotation":0,"startpos":0},{"template":"ConstructionDroid","id":419,"position":[1216,1472],"rotation":0,"startpos":0},{"template":"ConstructionDroid","id":420,"position":[1472,1216],"rotation":0,"startpos":0},{"template":"ConstructionDroid","id":421,"position":[1472,1088],"rotation":0,"startpos":0},{"template":"ConstructionDroid","id":469,"position":[11584,1472],"rotation":0,"startpos":1},{"template":"ConstructionDroid","id":470,"position":[11712,1472],"rotation":0,"startpos":1},{"template":"ConstructionDroid","id":471,"position":[11328,1216],"rotation":0,"startpos":1},{"template":"ConstructionDroid","id":472,"position":[11328,1088],"rotation":0,"startpos":1},{"template":"ConstructionDroid","id":497,"position":[1472,11712],"rotation":0,"startpos":2},{"template":"ConstructionDroid","id":498,"position":[1472,11584],"rotation":0,"startpos":2},{"template":"ConstructionDroid","id":499,"position":[1216,11328],"rotation":0,"startpos":2},{"template":"ConstructionDroid","id":500,"position":[1088,11328],"rotation":0,"startpos":2}]}