{"version":2,"droids":[{"template":"PythonHvyCnTrks","id":1676,"position":[14912,19520],"rotation":0,"player":"scavenger"},{"template":"A-Cobra-Trk-HMG","id":692,"position":[832,21440],"rotation":0,"player":"scavenger"},{"template":"ConstructionDroid","id":584,"position":[2368,21696],"rotation":0,"startpos":1},{"template":"A-Cobra-Trk-HMG","id":290,"position":[14528,3008],"rotation":0,"player":"scavenger"},{"template":"ConstructionDroid","id":590,"position":[20032,2368],"rotation":0,"startpos":0},{"template":"A-Cobra-Trk-HMG","id":289,"position":[14528,3264],"rotation":0,"player":"scavenger"},{"template":"A-Cobra-Trk-HMG","id":699,"position":[3008,25152],"rotation":0,"player":"scavenger"},{"template":"A-Cobra-Trk-HMG","id":691,"position":[704,21440],"rotation":0,"player":"scavenger"},{"template":"CobraMedCnTrks","id":250,"position":[19648,6592],"rotation":0,"player":"scavenger"},{"template":"CobraMedCnTrks","id":1888,"position":[2880,2624],"rotation":0,"startpos":2},{"template":"A-Cobra-Trk-HMG","id":133,"position":[20672,576],"rotation":0,"player":"scavenger"},{"template":"A-Cobra-Trk-HMG","id":130,"position":[20800,832],"rotation":0,"player":"scavenger"},{"template":"CobraFlameTracks","id":1599,"position":[2752,25152],"rotation":0,"player":"scavenger"},{"template":"PythonHvyCnTrks","id":1688,"position":[1984,6336],"rotation":0,"player":"scavenger"},{"template":"A-Cobra-Trk-HMG","id":129,"position":[20800,704],"rotation":0,"player":"scavenger"},{"template":"PythonHvyCnTrks","id":1687,"position":[1856,6336],"rotation":0,"player":"scavenger"},{"template":"PythonHvyCnTrks","id":1686,"position":[1728,6336],"rotation":0,"player":"scavenger"},{"template":"CobraFlameTracks","id":1598,"position":[2624,25152],"rotation":0,"player":"scavenger"},{"template":"A-Cobra-Trk-HMG","id":132,"position":[20672,704],"rotation":0,"player":"scavenger"},{"template":"A-Cobra-Trk-HMG","id":131,"position":[20672,832],"rotation":0,"player":"scavenger"},{"template":"CobraMedCnTrks","id":1887,"position":[2240,3264],"rotation":16384,"startpos":2},{"template":"A-Cobra-Trk-HMG","id":128,"position":[20800,576],"rotation":0,"player":"scavenger"},{"template":"A-Cobra-Trk-HMG","id":127,"position":[21696,4800],"rotation":0,"player":"scavenger"},{"template":"A-Cobra-Trk-HMG","id":126,"position":[22336,4800],"rotation":0,"player":"scavenger"},{"template":"CobraMedCnTrks","id":258,"position":[15424,3648],"rotation":0,"player":"scavenger"},{"template":"CobraMedCnTrks","id":252,"position":[20160,6592],"rotation":0,"player":"scavenger"},{"template":"CobraMedCnTrks","id":251,"position":[19904,6592],"rotation":0,"player":"scavenger"},{"template":"CobraMedCnTrks","id":1129,"position":[5952,2112],"rotation":16384,"player":"scavenger"},{"template":"PythonHvyCnTrks","id":1685,"position":[13888,24896],"rotation":0,"player":"scavenger"},{"template":"PythonHvyCnTrks","id":1684,"position":[13888,24768],"rotation":0,"player":"scavenger"},{"template":"PythonHvyCnTrks","id":1683,"position":[13888,24640],"rotation":0,"player":"scavenger"},{"template":"PythonHvyCnTrks","id":1682,"position":[13888,24512],"rotation":0,"player":"scavenger"},{"template":"CobraFlameTracks","id":1597,"position":[1600,18368],"rotation":0,"player":"scavenger"},{"template":"PythonHvyCnTrks","id":1681,"position":[13888,24384],"rotation":0,"player":"scavenger"},{"template":"CobraFlameTracks","id":1596,"position":[1472,18368],"rotation":0,"player":"scavenger"},{"template":"Cobra-Trk-Com","id":1595,"position":[832,21696],"rotation":0,"player":"scavenger"},{"template":"CobraMedCnTrks","id":1028,"position":[19520,24512],"rotation":16384,"player":"scavenger"},{"template":"Cobra-Trk-Com","id":1594,"position":[20416,704],"rotation":0,"player":"scavenger"},{"template":"CobraMedCnTrks","id":627,"position":[1984,15936],"rotation":16384,"player":"scavenger"},{"template":"CobraMedCnTrks","id":755,"position":[6336,19392],"rotation":0,"player":"scavenger"},{"template":"CobraHMGHalfTrack","id":1127,"position":[6208,2240],"rotation":16384,"player":"scavenger"},{"template":"CobraMedCnTrks","id":1130,"position":[5952,2240],"rotation":16384,"player":"scavenger"},{"template":"CobraMedCnTrks","id":1131,"position":[5952,2368],"rotation":16384,"player":"scavenger"},{"template":"CobraHMGHalfTrack","id":1126,"position":[6208,1984],"rotation":16384,"player":"scavenger"},{"template":"A-Cobra-Trk-HMG","id":760,"position":[8640,17216],"rotation":0,"player":"scavenger"},{"template":"A-Cobra-Trk-HMG","id":759,"position":[8640,17344],"rotation":0,"player":"scavenger"},{"template":"A-Cobra-Trk-HMG","id":758,"position":[8512,17344],"rotation":0,"player":"scavenger"},{"template":"CobraMedCnTrks","id":1128,"position":[5952,1984],"rotation":16384,"player":"scavenger"},{"template":"CobraHMGHalfTrack","id":1125,"position":[6208,2112],"rotation":16384,"player":"scavenger"},{"template":"PythonHvyCnTrks","id":1680,"position":[15424,19520],"rotation":0,"player":"scavenger"},{"template":"CobraHMGHalfTrack","id":1035,"position":[19776,24768],"rotation":16384,"player":"scavenger"},{"template":"CobraHMGHalfTrack","id":1034,"position":[19776,24896],"rotation":16384,"player":"scavenger"},{"template":"CobraHMGHalfTrack","id":1033,"position":[19776,24640],"rotation":16384,"player":"scavenger"},{"template":"CobraHMGHalfTrack","id":1032,"position":[19776,24512],"rotation":16384,"player":"scavenger"},{"template":"CobraMedCnTrks","id":1031,"position":[19520,24896],"rotation":16384,"player":"scavenger"},{"template":"PythonHvyCnTrks","id":1679,"position":[15296,19520],"rotation":0,"player":"scavenger"},{"template":"PythonHvyCnTrks","id":1678,"position":[15168,19520],"rotation":0,"player":"scavenger"},{"template":"PythonHvyCnTrks","id":1677,"position":[15040,19520],"rotation":0,"player":"scavenger"},{"template":"CobraMedCnTrks","id":1030,"position":[19520,24768],"rotation":16384,"player":"scavenger"},{"template":"CobraMedCnTrks","id":1029,"position":[19520,24640],"rotation":16384,"player":"scavenger"},{"template":"A-Cobra-Trk-HMG","id":757,"position":[8512,17216],"rotation":0,"player":"scavenger"},{"template":"CobraMedCnTrks","id":754,"position":[6336,19648],"rotation":0,"player":"scavenger"},{"template":"A-Cobra-Trk-HMG","id":690,"position":[1856,18368],"rotation":0,"player":"scavenger"},{"template":"CobraMedCnTrks","id":756,"position":[6336,19136],"rotation":0,"player":"scavenger"},{"template":"WyvernScourgeTracks","id":456,"position":[18240,11200],"rotation":16384,"player":"scavenger"},{"template":"PythonHvyCnTrks","id":454,"position":[19776,12992],"rotation":16384,"player":"scavenger"},{"template":"A-Cobra-Trk-HMG","id":288,"position":[14528,3520],"rotation":0,"player":"scavenger"},{"template":"WyvernScourgeTracks","id":459,"position":[17984,10560],"rotation":16384,"player":"scavenger"},{"template":"WyvernScourgeTracks","id":458,"position":[17984,10688],"rotation":16384,"player":"scavenger"},{"template":"WyvernScourgeTracks","id":457,"position":[18240,11072],"rotation":16384,"player":"scavenger"},{"template":"ViperLtCannonHTracks","id":589,"position":[19008,3008],"rotation":0,"startpos":0},{"template":"PythonHvyCnTrks","id":453,"position":[19904,12864],"rotation":16384,"player":"scavenger"},{"template":"PythonHvyCnTrks","id":451,"position":[15680,8128],"rotation":16384,"player":"scavenger"},{"template":"PythonHvyCnTrks","id":450,"position":[15552,8128],"rotation":16384,"player":"scavenger"},{"template":"PythonHvyCnTrks","id":448,"position":[13504,12224],"rotation":16384,"player":"scavenger"},{"template":"A-Cobra-Trk-HMG","id":294,"position":[22976,6208],"rotation":0,"player":"scavenger"},{"template":"A-Cobra-Trk-HMG","id":293,"position":[22976,6080],"rotation":0,"player":"scavenger"},{"template":"A-Cobra-Trk-HMG","id":292,"position":[22848,6080],"rotation":0,"player":"scavenger"},{"template":"CobraMedCnTrks","id":260,"position":[15680,3904],"rotation":0,"player":"scavenger"},{"template":"CobraMedCnTrks","id":259,"position":[15552,3776],"rotation":0,"player":"scavenger"},{"template":"A-Cobra-Trk-HMG","id":291,"position":[22848,6208],"rotation":0,"player":"scavenger"},{"template":"ViperLtCannonHTracks","id":588,"position":[18752,2880],"rotation":0,"startpos":0},{"template":"A-Cobra-Trk-HMG","id":689,"position":[1216,18368],"rotation":0,"player":"scavenger"},{"template":"ViperLtCannonHTracks","id":586,"position":[1728,20672],"rotation":0,"startpos":1},{"template":"Cyb-Chain-GROUND","id":633,"position":[1728,15808],"rotation":16384,"player":"scavenger"},{"template":"Cyb-Chain-GROUND","id":632,"position":[1600,15808],"rotation":16384,"player":"scavenger"},{"template":"Cyb-Chain-GROUND","id":631,"position":[1600,15936],"rotation":16384,"player":"scavenger"},{"template":"A-Cobra-Trk-HMG","id":698,"position":[2368,25152],"rotation":0,"player":"scavenger"},{"template":"A-Cobra-Trk-HMG","id":696,"position":[704,21568],"rotation":0,"player":"scavenger"},{"template":"A-Cobra-Trk-HMG","id":695,"position":[832,21568],"rotation":0,"player":"scavenger"},{"template":"A-Cobra-Trk-HMG","id":694,"position":[960,21568],"rotation":0,"player":"scavenger"},{"template":"A-Cobra-Trk-HMG","id":693,"position":[960,21440],"rotation":0,"player":"scavenger"},{"template":"Cyb-Chain-GROUND","id":630,"position":[1728,15936],"rotation":16384,"player":"scavenger"},{"template":"CobraMedCnTrks","id":626,"position":[1984,16064],"rotation":16384,"player":"scavenger"},{"template":"ConstructionDroid","id":585,"position":[2496,21696],"rotation":0,"startpos":1},{"template":"CobraMedCnTrks","id":628,"position":[1984,15808],"rotation":16384,"player":"scavenger"},{"template":"A-Cobra-Trk-HMG","id":125,"position":[17728,960],"rotation":0,"player":"scavenger"},{"template":"A-Cobra-Trk-HMG","id":124,"position":[17088,960],"rotation":0,"player":"scavenger"},{"template":"CobraHMGHalfTrack","id":1124,"position":[6208,2368],"rotation":16384,"player":"scavenger"},{"template":"PythonHvyCnTrks","id":1689,"position":[2112,6336],"rotation":0,"player":"scavenger"},{"template":"PythonHvyCnTrks","id":1695,"position":[13376,3136],"rotation":0,"player":"scavenger"},{"template":"PythonHvyCnTrks","id":1694,"position":[13376,3392],"rotation":0,"player":"scavenger"},{"template":"PythonHvyCnTrks","id":1693,"position":[13376,3264],"rotation":0,"player":"scavenger"},{"template":"PythonHvyCnTrks","id":1692,"position":[13376,3008],"rotation":0,"player":"scavenger"},{"template":"PythonHvyCnTrks","id":1691,"position":[13376,2880],"rotation":0,"player":"scavenger"},{"template":"PythonHvyCnTrks","id":1690,"position":[2240,6336],"rotation":0,"player":"scavenger"},{"template":"ConstructionDroid","id":591,"position":[20032,2496],"rotation":0,"startpos":0},{"template":"PythonHvyCnTrks","id":449,"position":[13376,12096],"rotation":16384,"player":"scavenger"},{"template":"PythonHvyCnTrks","id":447,"position":[13632,12352],"rotation":16384,"player":"scavenger"},{"template":"PythonHvyCnTrks","id":455,"position":[19648,13120],"rotation":16384,"player":"scavenger"},{"template":"PythonHvyCnTrks","id":452,"position":[15808,8128],"rotation":16384,"player":"scavenger"},{"template":"ViperLtCannonHTracks","id":587,"position":[1984,20672],"rotation":0,"startpos":1},{"template":"CobraMedCnTrks","id":629,"position":[1984,15680],"rotation":16384,"player":"scavenger"},{"template":"Cyb-Chain-GROUND","id":93,"position":[24640,3264],"rotation":0,"player":"scavenger"},{"template":"NP-L-Sensor-Wheels","id":94,"position":[24256,2752],"rotation":0,"player":"scavenger"},{"template":"Cyb-Chain-GROUND","id":92,"position":[24768,3264],"rotation":0,"player":"scavenger"},{"template":"CobraMedCnTrks","id":86,"position":[24512,2880],"rotation":0,"player":"scavenger"},{"template":"CobraMedCnTrks","id":87,"position":[24640,2880],"rotation":0,"player":"scavenger"},{"template":"CobraMedCnTrks","id":88,"position":[24768,2880],"rotation":0,"player":"scavenger"},{"template":"CobraMedCnTrks","id":89,"position":[24896,2880],"rotation":0,"player":"scavenger"},{"template":"Cyb-Chain-GROUND","id":90,"position":[24640,3136],"rotation":0,"player":"scavenger"},{"template":"Cyb-Chain-GROUND","id":91,"position":[24768,3136],"rotation":0,"player":"scavenger"},{"template":"CobraFlameTracks","id":120,"position":[21952,4928],"rotation":0,"player":"scavenger"},{"template":"CobraFlameTracks","id":121,"position":[22080,4928],"rotation":0,"player":"scavenger"},{"template":"CobraFlameTracks","id":122,"position":[17344,832],"rotation":0,"player":"scavenger"},{"template":"CobraFlameTracks","id":123,"position":[17472,832],"rotation":0,"player":"scavenger"},{"template":"CobraMedCnTrks","id":2045,"position":[24256,18752],"rotation":0,"startpos":3},{"template":"CobraMedCnTrks","id":2046,"position":[24512,18752],"rotation":0,"startpos":3},{"template":"ConstructionDroid","id":2047,"position":[24000,18240],"rotation":0,"startpos":3},{"template":"ConstructionDroid","id":2048,"position":[24128,17728],"rotation":0,"startpos":3},{"template":"ConstructionDroid","id":2049,"position":[1600,1088],"rotation":0,"startpos":2},{"template":"ConstructionDroid","id":2050,"position":[1088,1600],"rotation":0,"startpos":2}]}