{"version":2,"features":[{"name":"Pylon","id":267,"position":[4800,2112],"rotation":0},{"name":"Pylon","id":266,"position":[4800,1984],"rotation":0},{"name":"Pylon","id":265,"position":[4800,1856],"rotation":0},{"name":"Pylon","id":264,"position":[4800,1728],"rotation":0},{"name":"Pylon","id":263,"position":[4800,1600],"rotation":0},{"name":"Pylon","id":262,"position":[4800,1472],"rotation":0},{"name":"Pylon","id":261,"position":[4800,1344],"rotation":0},{"name":"Pylon","id":260,"position":[4800,1216],"rotation":0},{"name":"Pylon","id":259,"position":[4800,1088],"rotation":0},{"name":"Pylon","id":258,"position":[4800,960],"rotation":0},{"name":"Pylon","id":257,"position":[4800,832],"rotation":0},{"name":"Pylon","id":256,"position":[4800,704],"rotation":0},{"name":"Pylon","id":255,"position":[4800,576],"rotation":0},{"name":"Pylon","id":254,"position":[4800,448],"rotation":0},{"name":"Pylon","id":253,"position":[4800,320],"rotation":0},{"name":"Pylon","id":252,"position":[4672,320],"rotation":0},{"name":"Pylon","id":251,"position":[4544,320],"rotation":0},{"name":"Pylon","id":250,"position":[4416,320],"rotation":0},{"name":"Pylon","id":249,"position":[4288,320],"rotation":0},{"name":"Pylon","id":248,"position":[4160,320],"rotation":0},{"name":"Pylon","id":247,"position":[4032,320],"rotation":0},{"name":"Pylon","id":246,"position":[3904,320],"rotation":0},{"name":"Pylon","id":245,"position":[3776,320],"rotation":0},{"name":"Pylon","id":244,"position":[3648,320],"rotation":0},{"name":"Pylon","id":243,"position":[3520,320],"rotation":0},{"name":"Pylon","id":242,"position":[3392,320],"rotation":0},{"name":"Pylon","id":241,"position":[3264,320],"rotation":0},{"name":"Pylon","id":240,"position":[1728,320],"rotation":0},{"name":"Pylon","id":239,"position":[1600,320],"rotation":0},{"name":"Pylon","id":238,"position":[1472,320],"rotation":0},{"name":"Pylon","id":237,"position":[1344,320],"rotation":0},{"name":"Pylon","id":236,"position":[1216,320],"rotation":0},{"name":"OilResource","id":34,"position":[448,576],"rotation":0},{"name":"OilResource","id":35,"position":[576,576],"rotation":0},{"name":"OilResource","id":36,"position":[704,576],"rotation":0},{"name":"OilResource","id":37,"position":[832,576],"rotation":0},{"name":"OilResource","id":39,"position":[1088,576],"rotation":0},{"name":"OilResource","id":40,"position":[1216,576],"rotation":0},{"name":"OilResource","id":38,"position":[960,576],"rotation":0},{"name":"OilResource","id":41,"position":[1344,576],"rotation":0},{"name":"Pylon","id":290,"position":[3392,4800],"rotation":0},{"name":"Pylon","id":291,"position":[3520,4800],"rotation":0},{"name":"Pylon","id":280,"position":[4800,3776],"rotation":0},{"name":"Pylon","id":281,"position":[4800,3904],"rotation":0},{"name":"Pylon","id":269,"position":[4800,2368],"rotation":0},{"name":"Pylon","id":282,"position":[4800,4032],"rotation":0},{"name":"Pylon","id":270,"position":[4800,2496],"rotation":0},{"name":"Pylon","id":283,"position":[4800,4160],"rotation":0},{"name":"Pylon","id":276,"position":[4800,3264],"rotation":0},{"name":"Pylon","id":277,"position":[4800,3392],"rotation":0},{"name":"Pylon","id":271,"position":[4800,2624],"rotation":0},{"name":"Pylon","id":284,"position":[4800,4288],"rotation":0},{"name":"Pylon","id":285,"position":[4800,4416],"rotation":0},{"name":"Pylon","id":286,"position":[4800,4544],"rotation":0},{"name":"Pylon","id":287,"position":[4800,4672],"rotation":0},{"name":"Pylon","id":272,"position":[4800,2752],"rotation":0},{"name":"Pylon","id":278,"position":[4800,3520],"rotation":0},{"name":"Pylon","id":273,"position":[4800,2880],"rotation":0},{"name":"Pylon","id":279,"position":[4800,3648],"rotation":0},{"name":"Pylon","id":274,"position":[4800,3008],"rotation":0},{"name":"Pylon","id":275,"position":[4800,3136],"rotation":0},{"name":"Pylon","id":288,"position":[4800,4800],"rotation":0},{"name":"Pylon","id":289,"position":[3264,4800],"rotation":0},{"name":"Pylon","id":297,"position":[4288,4800],"rotation":0},{"name":"Pylon","id":298,"position":[4416,4800],"rotation":0},{"name":"Pylon","id":292,"position":[3648,4800],"rotation":0},{"name":"Pylon","id":293,"position":[3776,4800],"rotation":0},{"name":"Pylon","id":299,"position":[4544,4800],"rotation":0},{"name":"Pylon","id":300,"position":[4672,4800],"rotation":0},{"name":"Pylon","id":296,"position":[4160,4800],"rotation":0},{"name":"Pylon","id":294,"position":[3904,4800],"rotation":0},{"name":"Pylon","id":295,"position":[4032,4800],"rotation":0},{"name":"OilResource","id":133,"position":[832,4416],"rotation":0},{"name":"Pylon","id":235,"position":[1088,320],"rotation":0},{"name":"OilResource","id":155,"position":[704,4416],"rotation":0},{"name":"OilResource","id":141,"position":[1088,4416],"rotation":0},{"name":"OilResource","id":134,"position":[960,4416],"rotation":0},{"name":"OilResource","id":142,"position":[1216,4416],"rotation":0},{"name":"OilResource","id":149,"position":[1344,4416],"rotation":0},{"name":"OilResource","id":151,"position":[1472,4416],"rotation":0},{"name":"OilResource","id":154,"position":[576,4416],"rotation":0},{"name":"Pylon","id":268,"position":[4800,2240],"rotation":0},{"name":"Pylon","id":180,"position":[2624,1728],"rotation":0},{"name":"Pylon","id":181,"position":[192,320],"rotation":0},{"name":"Pylon","id":182,"position":[192,448],"rotation":0},{"name":"Pylon","id":183,"position":[192,576],"rotation":0},{"name":"Pylon","id":184,"position":[192,704],"rotation":0},{"name":"Pylon","id":185,"position":[192,832],"rotation":0},{"name":"Pylon","id":186,"position":[192,960],"rotation":0},{"name":"Pylon","id":187,"position":[192,1088],"rotation":0},{"name":"Pylon","id":188,"position":[192,1216],"rotation":0},{"name":"Pylon","id":189,"position":[192,1344],"rotation":0},{"name":"Pylon","id":190,"position":[192,1472],"rotation":0},{"name":"Pylon","id":191,"position":[192,1600],"rotation":0},{"name":"Pylon","id":192,"position":[192,1728],"rotation":0},{"name":"Pylon","id":193,"position":[192,1856],"rotation":0},{"name":"Pylon","id":194,"position":[192,1984],"rotation":0},{"name":"Pylon","id":195,"position":[192,2112],"rotation":0},{"name":"Pylon","id":196,"position":[192,2240],"rotation":0},{"name":"Pylon","id":197,"position":[192,2368],"rotation":0},{"name":"Pylon","id":198,"position":[192,2496],"rotation":0},{"name":"Pylon","id":199,"position":[192,2624],"rotation":0},{"name":"Pylon","id":200,"position":[192,2752],"rotation":0},{"name":"Pylon","id":201,"position":[192,2880],"rotation":0},{"name":"Pylon","id":202,"position":[192,3008],"rotation":0},{"name":"Pylon","id":203,"position":[192,3136],"rotation":0},{"name":"Pylon","id":204,"position":[192,3264],"rotation":0},{"name":"Pylon","id":205,"position":[192,3392],"rotation":0},{"name":"Pylon","id":206,"position":[192,3520],"rotation":0},{"name":"Pylon","id":207,"position":[192,3648],"rotation":0},{"name":"Pylon","id":208,"position":[192,3776],"rotation":0},{"name":"Pylon","id":209,"position":[192,3904],"rotation":0},{"name":"Pylon","id":210,"position":[192,4032],"rotation":0},{"name":"Pylon","id":211,"position":[192,4160],"rotation":0},{"name":"Pylon","id":212,"position":[192,4288],"rotation":0},{"name":"Pylon","id":213,"position":[192,4416],"rotation":0},{"name":"Pylon","id":214,"position":[192,4544],"rotation":0},{"name":"Pylon","id":215,"position":[192,4672],"rotation":0},{"name":"Pylon","id":216,"position":[192,4800],"rotation":0},{"name":"Pylon","id":217,"position":[320,4800],"rotation":0},{"name":"Pylon","id":218,"position":[448,4800],"rotation":0},{"name":"Pylon","id":219,"position":[576,4800],"rotation":0},{"name":"Pylon","id":220,"position":[704,4800],"rotation":0},{"name":"Pylon","id":221,"position":[832,4800],"rotation":0},{"name":"Pylon","id":222,"position":[960,4800],"rotation":0},{"name":"Pylon","id":223,"position":[1088,4800],"rotation":0},{"name":"Pylon","id":224,"position":[1216,4800],"rotation":0},{"name":"Pylon","id":225,"position":[1344,4800],"rotation":0},{"name":"Pylon","id":226,"position":[1472,4800],"rotation":0},{"name":"Pylon","id":227,"position":[1600,4800],"rotation":0},{"name":"Pylon","id":228,"position":[1728,4800],"rotation":0},{"name":"Pylon","id":229,"position":[320,320],"rotation":0},{"name":"Pylon","id":230,"position":[448,320],"rotation":0},{"name":"Pylon","id":231,"position":[576,320],"rotation":0},{"name":"Pylon","id":232,"position":[704,320],"rotation":0},{"name":"Pylon","id":233,"position":[832,320],"rotation":0},{"name":"Pylon","id":234,"position":[960,320],"rotation":0},{"name":"OilResource","id":301,"position":[3520,576],"rotation":0},{"name":"OilResource","id":302,"position":[3648,576],"rotation":0},{"name":"OilResource","id":304,"position":[3904,576],"rotation":0},{"name":"OilResource","id":305,"position":[4032,576],"rotation":0},{"name":"OilResource","id":306,"position":[4160,576],"rotation":0},{"name":"OilResource","id":307,"position":[4288,576],"rotation":0},{"name":"OilResource","id":308,"position":[3776,576],"rotation":0},{"name":"OilResource","id":311,"position":[4416,576],"rotation":0},{"name":"OilResource","id":334,"position":[4416,4416],"rotation":0},{"name":"OilResource","id":337,"position":[4032,4416],"rotation":0},{"name":"OilResource","id":338,"position":[3904,4416],"rotation":0},{"name":"OilResource","id":339,"position":[3776,4416],"rotation":0},{"name":"OilResource","id":335,"position":[4288,4416],"rotation":0},{"name":"OilResource","id":341,"position":[4160,4416],"rotation":0},{"name":"OilResource","id":340,"position":[3648,4416],"rotation":0},{"name":"OilResource","id":344,"position":[3520,4416],"rotation":0}]}