{"version":2,"droids":[{"template":"ConstructionDroid","id":40,"position":[832,1088],"rotation":0,"startpos":0},{"template":"ConstructionDroid","id":41,"position":[960,1088],"rotation":0,"startpos":0},{"template":"ConstructionDroid","id":42,"position":[1088,1088],"rotation":0,"startpos":0},{"template":"ConstructionDroid","id":43,"position":[1216,1088],"rotation":0,"startpos":0},{"template":"ConstructionDroid","id":44,"position":[1344,1088],"rotation":0,"startpos":0},{"template":"ConstructionDroid","id":45,"position":[1472,1088],"rotation":0,"startpos":0},{"template":"ConstructionDroid","id":46,"position":[1600,1088],"rotation":0,"startpos":0},{"template":"ConstructionDroid","id":47,"position":[1728,1088],"rotation":0,"startpos":0},{"template":"ConstructionDroid","id":48,"position":[1856,1088],"rotation":0,"startpos":0},{"template":"ConstructionDroid","id":49,"position":[1984,1088],"rotation":0,"startpos":0},{"template":"ConstructionDroid","id":155,"position":[23360,1216],"rotation":0,"startpos":1},{"template":"ConstructionDroid","id":156,"position":[23232,1216],"rotation":0,"startpos":1},{"template":"ConstructionDroid","id":157,"position":[23104,1216],"rotation":0,"startpos":1},{"template":"ConstructionDroid","id":158,"position":[22976,1216],"rotation":0,"startpos":1},{"template":"ConstructionDroid","id":159,"position":[22848,1216],"rotation":0,"startpos":1},{"template":"ConstructionDroid","id":160,"position":[22720,1216],"rotation":0,"startpos":1},{"template":"ConstructionDroid","id":161,"position":[22592,1216],"rotation":0,"startpos":1},{"template":"ConstructionDroid","id":162,"position":[22464,1216],"rotation":0,"startpos":1},{"template":"ConstructionDroid","id":163,"position":[22336,1216],"rotation":0,"startpos":1},{"template":"ConstructionDroid","id":164,"position":[22208,1216],"rotation":0,"startpos":1},{"template":"ConstructionDroid","id":270,"position":[960,23232],"rotation":0,"startpos":2},{"template":"ConstructionDroid","id":271,"position":[1088,23232],"rotation":0,"startpos":2},{"template":"ConstructionDroid","id":272,"position":[1216,23232],"rotation":0,"startpos":2},{"template":"ConstructionDroid","id":273,"position":[1344,23232],"rotation":0,"startpos":2},{"template":"ConstructionDroid","id":274,"position":[1472,23232],"rotation":0,"startpos":2},{"template":"ConstructionDroid","id":275,"position":[1600,23232],"rotation":0,"startpos":2},{"template":"ConstructionDroid","id":276,"position":[1728,23232],"rotation":0,"startpos":2},{"template":"ConstructionDroid","id":277,"position":[1856,23232],"rotation":0,"startpos":2},{"template":"ConstructionDroid","id":278,"position":[1984,23232],"rotation":0,"startpos":2},{"template":"ConstructionDroid","id":279,"position":[2112,23232],"rotation":0,"startpos":2},{"template":"ConstructionDroid","id":384,"position":[22208,23232],"rotation":0,"startpos":3},{"template":"ConstructionDroid","id":385,"position":[22336,23232],"rotation":0,"startpos":3},{"template":"ConstructionDroid","id":386,"position":[22464,23232],"rotation":0,"startpos":3},{"template":"ConstructionDroid","id":387,"position":[22592,23232],"rotation":0,"startpos":3},{"template":"ConstructionDroid","id":388,"position":[22720,23232],"rotation":0,"startpos":3},{"template":"ConstructionDroid","id":389,"position":[22848,23232],"rotation":0,"startpos":3},{"template":"ConstructionDroid","id":390,"position":[22976,23232],"rotation":0,"startpos":3},{"template":"ConstructionDroid","id":391,"position":[23104,23232],"rotation":0,"startpos":3},{"template":"ConstructionDroid","id":392,"position":[23232,23232],"rotation":0,"startpos":3},{"template":"ConstructionDroid","id":393,"position":[23360,23232],"rotation":0,"startpos":3}]}