{"version":2,"features":[{"name":"TreeSnow3","id":2456,"position":[7232,10688],"rotation":64079},{"name":"OilResource","id":545,"position":[5952,11712],"rotation":0},{"name":"Tree3","id":2784,"position":[7744,6464],"rotation":32585},{"name":"OilResource","id":2463,"position":[5952,11072],"rotation":0},{"name":"Tree3","id":1629,"position":[2240,8896],"rotation":28945},{"name":"Tree3","id":1613,"position":[1856,10176],"rotation":51518},{"name":"TreeSnow3","id":1363,"position":[5568,10304],"rotation":61531},{"name":"Tree3","id":2065,"position":[3008,11200],"rotation":40960},{"name":"Tree3","id":1543,"position":[2880,12096],"rotation":4915},{"name":"TreeSnow3","id":2018,"position":[3648,8512],"rotation":32950},{"name":"TreeSnow3","id":2016,"position":[3008,8000],"rotation":22755},{"name":"Tree3","id":2107,"position":[1472,13504],"rotation":28580},{"name":"Tree3","id":1593,"position":[3520,14144],"rotation":56797},{"name":"Tree3","id":1596,"position":[2880,9920],"rotation":37683},{"name":"Tree1","id":2073,"position":[1152,13696],"rotation":28580},{"name":"Tree3","id":2081,"position":[1472,11712],"rotation":56251},{"name":"Tree1","id":2091,"position":[1408,14848],"rotation":23483},{"name":"Tree3","id":1557,"position":[3008,12608],"rotation":54431},{"name":"Tree1","id":1579,"position":[4352,9856],"rotation":40777},{"name":"Tree3","id":1518,"position":[3776,10048],"rotation":6371},{"name":"Tree1","id":2085,"position":[1664,12544],"rotation":4733},{"name":"Tree1","id":2077,"position":[1152,14080],"rotation":35498},{"name":"Tree1","id":1594,"position":[2688,9856],"rotation":38593},{"name":"TreeSnow3","id":1366,"position":[7488,9152],"rotation":728},{"name":"Tree3","id":1578,"position":[3776,9536],"rotation":42052},{"name":"Tree3","id":1628,"position":[448,9152],"rotation":57526},{"name":"Tree1","id":839,"position":[5888,10880],"rotation":32768},{"name":"Tree3","id":1541,"position":[3776,12480],"rotation":17476},{"name":"Chevy","id":1564,"position":[4160,12480],"rotation":60256},{"name":"TreeSnow3","id":1638,"position":[3904,12736],"rotation":59892},{"name":"Tree3","id":1560,"position":[4160,10560],"rotation":2366},{"name":"TreeSnow3","id":2017,"position":[5440,8384],"rotation":24758},{"name":"Tree3","id":2103,"position":[576,11712],"rotation":58254},{"name":"Tree3","id":2086,"position":[1856,13504],"rotation":43508},{"name":"Tree1","id":2080,"position":[512,11904],"rotation":59346},{"name":"Tree1","id":1618,"position":[640,9472],"rotation":49698},{"name":"Tree3","id":2068,"position":[2880,10944],"rotation":17658},{"name":"TreeSnow3","id":2020,"position":[4160,7744],"rotation":32403},{"name":"TreeSnow3","id":2019,"position":[4928,8896],"rotation":37137},{"name":"TreeSnow3","id":2097,"position":[704,12864],"rotation":44236},{"name":"Tree3","id":2108,"position":[1344,13376],"rotation":3458},{"name":"Tree1","id":1631,"position":[2176,8704],"rotation":17658},{"name":"Tree3","id":2106,"position":[1728,12352],"rotation":57526},{"name":"TreeSnow3","id":1633,"position":[3520,13504],"rotation":26760},{"name":"WaterTower","id":1572,"position":[4032,12480],"rotation":0},{"name":"Tree3","id":2071,"position":[2496,11200],"rotation":62805},{"name":"Tree1","id":2067,"position":[3072,10880],"rotation":52792},{"name":"TreeSnow3","id":2015,"position":[3264,8128],"rotation":13471},{"name":"TreeSnow3","id":1639,"position":[3520,12736],"rotation":34588},{"name":"Tree1","id":2104,"position":[1024,11136],"rotation":9284},{"name":"TreeSnow3","id":2079,"position":[960,12608],"rotation":40049},{"name":"Tree3","id":2064,"position":[2624,11328],"rotation":44054},{"name":"Tree1","id":2072,"position":[1536,12032],"rotation":2548},{"name":"OilTower","id":1562,"position":[4288,12608],"rotation":0},{"name":"Tree3","id":2088,"position":[1216,11200],"rotation":55887},{"name":"Tree3","id":604,"position":[7872,12864],"rotation":52792},{"name":"Tree1","id":1522,"position":[3328,9472],"rotation":59528},{"name":"Tree3","id":2082,"position":[1856,11840],"rotation":18932},{"name":"TreeSnow3","id":2090,"position":[448,13120],"rotation":26942},{"name":"Tree1","id":1567,"position":[3968,10112],"rotation":23847},{"name":"Tree3","id":2089,"position":[1600,12864],"rotation":1820},{"name":"TreeSnow3","id":2099,"position":[960,12096],"rotation":60074},{"name":"Tree3","id":2066,"position":[3264,10944],"rotation":11286},{"name":"Tree3","id":1548,"position":[3520,12224],"rotation":5279},{"name":"Tree1","id":2094,"position":[896,11392],"rotation":6553},{"name":"TreeSnow3","id":2087,"position":[448,14656],"rotation":7645},{"name":"Tree3","id":2100,"position":[1856,13248],"rotation":2366},{"name":"Tree3","id":1605,"position":[3264,12096],"rotation":24758},{"name":"TreeSnow1","id":2078,"position":[512,12928],"rotation":49152},{"name":"TreeSnow3","id":2092,"position":[1088,12352],"rotation":20571},{"name":"Tree1","id":2105,"position":[1280,14592],"rotation":8192},{"name":"Tree1","id":2102,"position":[1664,11776],"rotation":53885},{"name":"TreeSnow3","id":2093,"position":[1344,12224],"rotation":18386},{"name":"Tree1","id":2069,"position":[2688,11136],"rotation":41870},{"name":"Tree3","id":2095,"position":[1216,11456],"rotation":44054},{"name":"Tree1","id":2083,"position":[1792,13056],"rotation":31311},{"name":"TreeSnow3","id":1632,"position":[3520,13632],"rotation":8920},{"name":"Tree1","id":2076,"position":[1664,13440],"rotation":12925},{"name":"OilTower","id":1563,"position":[4160,12608],"rotation":0},{"name":"Tree1","id":2075,"position":[1792,12160],"rotation":32768},{"name":"WreckedSuzukiJeep","id":1571,"position":[3776,12224],"rotation":49334},{"name":"Tree3","id":2084,"position":[1088,14400],"rotation":41688},{"name":"Tree3","id":2096,"position":[832,11584],"rotation":56979},{"name":"OilResource","id":2010,"position":[3776,7744],"rotation":0},{"name":"WaterTower","id":1407,"position":[8384,8000],"rotation":0},{"name":"Tree1","id":2098,"position":[1280,11648],"rotation":31311},{"name":"Tree1","id":2074,"position":[896,11776],"rotation":64079},{"name":"Tree3","id":2101,"position":[1216,13888],"rotation":4187},{"name":"TreeSnow3","id":1637,"position":[4032,12992],"rotation":54795},{"name":"TreeSnow3","id":1640,"position":[3392,12736],"rotation":62441},{"name":"TreeSnow3","id":1361,"position":[5952,10176],"rotation":12196},{"name":"Tree3","id":1589,"position":[448,9664],"rotation":38593},{"name":"TreeSnow3","id":1693,"position":[5824,9664],"rotation":8738},{"name":"Tree3","id":1600,"position":[2752,13120],"rotation":16930},{"name":"BarbWarehouse3","id":263,"position":[4672,11968],"rotation":0},{"name":"Tree3","id":1517,"position":[4032,9920],"rotation":45147},{"name":"Pickup","id":261,"position":[4800,12480],"rotation":6189},{"name":"Tree3","id":1533,"position":[3008,12480],"rotation":64443},{"name":"BarbWarehouse3","id":1079,"position":[4800,12352],"rotation":0},{"name":"Tree3","id":1591,"position":[3008,12992],"rotation":52064},{"name":"Tree3","id":1592,"position":[2880,12864],"rotation":44236},{"name":"Tree3","id":1568,"position":[3520,9792],"rotation":8920},{"name":"Tree3","id":1624,"position":[1344,10304],"rotation":51700},{"name":"BarbWarehouse1","id":228,"position":[4480,12608],"rotation":0},{"name":"Tree1","id":1588,"position":[3968,13568],"rotation":61713},{"name":"TreeSnow3","id":1696,"position":[3264,9024],"rotation":13107},{"name":"TreeSnow3","id":1689,"position":[1856,8384],"rotation":47513},{"name":"Tree3","id":1620,"position":[1984,8640],"rotation":49516},{"name":"Tree3","id":1603,"position":[3904,13760],"rotation":44600},{"name":"Tree1","id":1610,"position":[2944,13440],"rotation":13835},{"name":"Tree3","id":1408,"position":[7616,8000],"rotation":33860},{"name":"TreeSnow3","id":1691,"position":[5824,9408],"rotation":25122},{"name":"OilResource","id":1523,"position":[4416,12352],"rotation":0},{"name":"Tree1","id":1606,"position":[3328,14080],"rotation":11650},{"name":"Tree3","id":268,"position":[4928,11840],"rotation":37137},{"name":"BarbWarehouse1","id":1410,"position":[8320,8384],"rotation":0},{"name":"TreeSnow3","id":2459,"position":[5696,9920],"rotation":22937},{"name":"Tree3","id":1586,"position":[4288,13760],"rotation":6189},{"name":"Tree3","id":846,"position":[6976,10816],"rotation":13835},{"name":"LogCabin1","id":1529,"position":[4032,11712],"rotation":0},{"name":"Tree1","id":1583,"position":[2944,8960],"rotation":19114},{"name":"TreeSnow1","id":1374,"position":[8064,10368],"rotation":23301},{"name":"TreeSnow3","id":1365,"position":[6464,10048],"rotation":20571},{"name":"Tree3","id":1627,"position":[960,9920],"rotation":5279},{"name":"BarbWarehouse1","id":1515,"position":[3968,12096],"rotation":0},{"name":"WreckedVertCampVan","id":230,"position":[4672,12608],"rotation":10012},{"name":"Tree3","id":310,"position":[4544,11200],"rotation":60074},{"name":"Tree1","id":1607,"position":[1152,9472],"rotation":26942},{"name":"TreeSnow3","id":1076,"position":[4672,10432],"rotation":910},{"name":"Tree3","id":1409,"position":[8512,8640],"rotation":6007},{"name":"Tree3","id":805,"position":[8384,11712],"rotation":29491},{"name":"BarbWarehouse3","id":1404,"position":[7872,8000],"rotation":0},{"name":"TreeSnow3","id":1695,"position":[3776,9152],"rotation":50608},{"name":"Tree3","id":1516,"position":[4288,10176],"rotation":58618},{"name":"Tree3","id":1622,"position":[2752,8768],"rotation":59164},{"name":"Tree3","id":1584,"position":[3008,13888],"rotation":52064},{"name":"OilResource","id":2458,"position":[5824,9792],"rotation":0},{"name":"TreeSnow3","id":1635,"position":[3648,13376],"rotation":51518},{"name":"TreeSnow3","id":1077,"position":[4672,10048],"rotation":42962},{"name":"Tree3","id":1626,"position":[704,10048],"rotation":28034},{"name":"OilResource","id":2457,"position":[6720,9408],"rotation":0},{"name":"TreeSnow3","id":1694,"position":[4800,9152],"rotation":34224},{"name":"Tree3","id":1617,"position":[2880,9152],"rotation":22391},{"name":"Tree3","id":266,"position":[4928,12096],"rotation":46785},{"name":"OilResource","id":1556,"position":[1472,9408],"rotation":0},{"name":"Tree1","id":437,"position":[4864,9472],"rotation":34770},{"name":"Tree3","id":595,"position":[4672,13760],"rotation":546},{"name":"TreeSnow3","id":1688,"position":[1600,8256],"rotation":48605},{"name":"Tree3","id":1542,"position":[2112,10304],"rotation":60802},{"name":"Tree3","id":593,"position":[5184,13248],"rotation":34042},{"name":"Tree3","id":1580,"position":[4416,13760],"rotation":10012},{"name":"Tree3","id":589,"position":[6080,13504],"rotation":14017},{"name":"Tree3","id":591,"position":[6080,13248],"rotation":33678},{"name":"BarbWarehouse3","id":1524,"position":[3776,12096],"rotation":0},{"name":"Tree3","id":1540,"position":[4032,10816],"rotation":16748},{"name":"Tree3","id":1585,"position":[4160,13504],"rotation":62805},{"name":"Tree3","id":588,"position":[6464,13888],"rotation":15837},{"name":"Tree3","id":605,"position":[6208,13760],"rotation":12014},{"name":"Tree3","id":586,"position":[6720,13632],"rotation":58254},{"name":"Tree3","id":443,"position":[4544,9792],"rotation":24029},{"name":"Tree3","id":1616,"position":[2880,12608],"rotation":62259},{"name":"TreeSnow3","id":1690,"position":[576,8768],"rotation":43144},{"name":"Tree3","id":583,"position":[7616,13376],"rotation":60802},{"name":"OilResource","id":1375,"position":[8256,7872],"rotation":0},{"name":"TreeSnow3","id":1370,"position":[8512,10944],"rotation":10012},{"name":"Tree3","id":606,"position":[7616,13632],"rotation":65353},{"name":"TreeSnow3","id":1636,"position":[3648,12992],"rotation":40960},{"name":"Tree3","id":790,"position":[7616,12224],"rotation":45511},{"name":"Tree3","id":792,"position":[7360,13888],"rotation":44054},{"name":"Tree3","id":579,"position":[7744,12096],"rotation":14199},{"name":"Tree1","id":1621,"position":[2432,10112],"rotation":14927},{"name":"Tree3","id":808,"position":[8000,11072],"rotation":9284},{"name":"Tree3","id":788,"position":[7872,11840],"rotation":45147},{"name":"Tree3","id":789,"position":[8000,12096],"rotation":20935},{"name":"Tree3","id":796,"position":[7104,13760],"rotation":35862},{"name":"Tree1","id":562,"position":[5888,13184],"rotation":1638},{"name":"Tree3","id":1538,"position":[2880,12224],"rotation":16201},{"name":"Crane","id":1552,"position":[4032,11968],"rotation":46421},{"name":"Tree3","id":584,"position":[7488,13632],"rotation":20024},{"name":"Tree3","id":592,"position":[5568,13376],"rotation":24940},{"name":"Tree1","id":559,"position":[4992,13184],"rotation":364},{"name":"Tree3","id":581,"position":[7360,12608],"rotation":19114},{"name":"Tree1","id":573,"position":[7552,12800],"rotation":32221},{"name":"Tree3","id":582,"position":[7872,13504],"rotation":30037},{"name":"Tree3","id":442,"position":[4672,9536],"rotation":24211},{"name":"Tree3","id":795,"position":[6848,13888],"rotation":53703},{"name":"TreeSnow3","id":1364,"position":[6336,10048],"rotation":6553},{"name":"Tree3","id":845,"position":[7360,11584],"rotation":58982},{"name":"Tree3","id":587,"position":[6976,14016],"rotation":32768},{"name":"Tree3","id":608,"position":[5056,13504],"rotation":42052},{"name":"Tree3","id":594,"position":[4800,13376],"rotation":3822},{"name":"TreeSnow3","id":1641,"position":[3392,12864],"rotation":20753},{"name":"Tree1","id":566,"position":[6656,13952],"rotation":6735},{"name":"Tree3","id":1598,"position":[4288,10816],"rotation":45147},{"name":"TreeSnow3","id":1369,"position":[8512,10048],"rotation":36955},{"name":"Tree3","id":844,"position":[5952,11968],"rotation":13107},{"name":"Tree3","id":791,"position":[7744,12480],"rotation":29309},{"name":"TreeSnow3","id":1075,"position":[5824,12480],"rotation":31857},{"name":"Tree3","id":793,"position":[7744,13120],"rotation":37319},{"name":"Tree3","id":794,"position":[4672,13504],"rotation":25668},{"name":"Tree3","id":590,"position":[5952,13504],"rotation":58436},{"name":"Tree1","id":439,"position":[4480,9344],"rotation":15655},{"name":"Tree1","id":1550,"position":[3584,12416],"rotation":61348},{"name":"TreeSnow3","id":1064,"position":[6976,12864],"rotation":59892},{"name":"Crane","id":1399,"position":[8384,7744],"rotation":21663},{"name":"TreeSnow1","id":1373,"position":[7168,10112],"rotation":56615},{"name":"Tree3","id":1590,"position":[1472,10304],"rotation":33496},{"name":"Tree3","id":578,"position":[8000,11840],"rotation":56069},{"name":"LogCabin1","id":1573,"position":[3904,11712],"rotation":0},{"name":"Tree3","id":842,"position":[6208,10688],"rotation":31675},{"name":"Tree3","id":804,"position":[8256,11712],"rotation":22937},{"name":"Tree3","id":807,"position":[8384,11328],"rotation":49334},{"name":"Tree3","id":1608,"position":[3648,13888],"rotation":49880},{"name":"Tree3","id":1630,"position":[704,9664],"rotation":44782},{"name":"TreeSnow3","id":1065,"position":[7232,13248],"rotation":22937},{"name":"Tree3","id":841,"position":[6080,10944],"rotation":7099},{"name":"OilTower","id":1406,"position":[8384,8256],"rotation":0},{"name":"BarbWarehouse1","id":1398,"position":[8192,7744],"rotation":0},{"name":"Tree3","id":840,"position":[5696,11200],"rotation":56797},{"name":"TreeSnow3","id":1634,"position":[3648,13504],"rotation":61166},{"name":"Tree3","id":810,"position":[7744,11328],"rotation":44236},{"name":"TreeSnow3","id":1046,"position":[4800,12864],"rotation":1092},{"name":"Tree3","id":1625,"position":[1088,10304],"rotation":10012},{"name":"TreeSnow3","id":1063,"position":[6592,13248],"rotation":63533},{"name":"Tree3","id":838,"position":[6720,12480],"rotation":27306},{"name":"Tree3","id":809,"position":[8128,11456],"rotation":14745},{"name":"TreeSnow3","id":1061,"position":[5440,12480],"rotation":36590},{"name":"TreeSnow3","id":1053,"position":[7488,11840],"rotation":37865},{"name":"Tree3","id":1602,"position":[3008,13632],"rotation":19296},{"name":"Tree3","id":1601,"position":[3008,13248],"rotation":12014},{"name":"Tree3","id":1566,"position":[3904,10432],"rotation":32039},{"name":"Tree1","id":806,"position":[8448,11520],"rotation":36408},{"name":"TreeSnow3","id":1643,"position":[3264,12480],"rotation":35680},{"name":"TreeSnow3","id":1047,"position":[5312,12992],"rotation":11104},{"name":"TreeSnow3","id":1052,"position":[7616,11840],"rotation":64625},{"name":"Tree3","id":1619,"position":[1216,8896],"rotation":65353},{"name":"TreeSnow3","id":1049,"position":[7360,12096],"rotation":26942},{"name":"TreeSnow3","id":1051,"position":[7616,11712],"rotation":24029},{"name":"TreeSnow3","id":1062,"position":[6464,12992],"rotation":53703},{"name":"BarbWarehouse2","id":1080,"position":[4864,11968],"rotation":0},{"name":"TreeSnow3","id":1072,"position":[5440,11840],"rotation":19842},{"name":"TreeSnow3","id":1050,"position":[7616,11584],"rotation":23119},{"name":"TreeSnow3","id":1060,"position":[5312,12608],"rotation":13107},{"name":"Tree3","id":1521,"position":[4288,9280],"rotation":56251},{"name":"TreeSnow3","id":1074,"position":[5440,12096],"rotation":2366},{"name":"TreeSnow3","id":1073,"position":[5440,11968],"rotation":21663},{"name":"Tree3","id":1612,"position":[3136,9408],"rotation":25850},{"name":"TreeSnow3","id":1048,"position":[7104,13504],"rotation":61348},{"name":"Tree3","id":1615,"position":[1472,9664],"rotation":20388},{"name":"Tree3","id":1595,"position":[3904,14016],"rotation":26396},{"name":"Tree3","id":1599,"position":[4288,11072],"rotation":8920},{"name":"Tree3","id":1597,"position":[4416,10816],"rotation":57708},{"name":"Tree3","id":1587,"position":[3136,13376],"rotation":37501},{"name":"TreeSnow3","id":1642,"position":[3264,12864],"rotation":182},{"name":"Tree1","id":1623,"position":[1408,8832],"rotation":10194},{"name":"Tree3","id":843,"position":[7104,11968],"rotation":24576},{"name":"OilResource","id":2460,"position":[1856,8768],"rotation":0},{"name":"TreeSnow3","id":1697,"position":[960,9024],"rotation":5279},{"name":"TreeSnow3","id":2785,"position":[1600,3264],"rotation":59710},{"name":"Tree3","id":2680,"position":[6080,6208],"rotation":55159},{"name":"Tree3","id":2758,"position":[1984,4544],"rotation":46603},{"name":"TreeSnow3","id":2746,"position":[3136,2880],"rotation":64625},{"name":"Tree3","id":2795,"position":[5824,5952],"rotation":58618},{"name":"Tree3","id":2797,"position":[7104,5184],"rotation":18750},{"name":"TreeSnow3","id":2547,"position":[3392,5056],"rotation":28763},{"name":"Tree3","id":2548,"position":[5952,4160],"rotation":8192},{"name":"Tree3","id":2549,"position":[6080,3264],"rotation":37683},{"name":"TreeSnow3","id":2550,"position":[5312,6848],"rotation":182},{"name":"TreeSnow3","id":2551,"position":[5952,7360],"rotation":55523},{"name":"Tree3","id":2552,"position":[7488,1856],"rotation":61348},{"name":"Tree3","id":2553,"position":[5440,1216],"rotation":24029},{"name":"Tree1","id":2555,"position":[7808,1664],"rotation":61348},{"name":"Tree3","id":2556,"position":[7488,3648],"rotation":23483},{"name":"Tree1","id":2557,"position":[7552,512],"rotation":56251},{"name":"Tree3","id":2558,"position":[5952,2752],"rotation":21663},{"name":"Tree1","id":2559,"position":[4608,5504],"rotation":8009},{"name":"Tree3","id":2560,"position":[5184,5312],"rotation":39139},{"name":"Tree1","id":2561,"position":[7296,2816],"rotation":37501},{"name":"Tree1","id":2562,"position":[7808,1280],"rotation":2730},{"name":"Tree3","id":2771,"position":[7872,5056],"rotation":42780},{"name":"TreeSnow3","id":2564,"position":[1472,6208],"rotation":33496},{"name":"Tree3","id":2565,"position":[5184,5824],"rotation":9284},{"name":"Tree3","id":2566,"position":[8512,6208],"rotation":24758},{"name":"Tree3","id":2567,"position":[5184,2880],"rotation":50244},{"name":"Chevy","id":2568,"position":[4800,2880],"rotation":27488},{"name":"Tree3","id":2755,"position":[6848,5056],"rotation":28034},{"name":"TreeSnow3","id":2570,"position":[5056,2624],"rotation":27124},{"name":"Tree3","id":2571,"position":[4800,4800],"rotation":35134},{"name":"TreeSnow3","id":2572,"position":[3520,6976],"rotation":57526},{"name":"Tree3","id":2573,"position":[8384,3648],"rotation":25486},{"name":"Tree3","id":2574,"position":[7104,1856],"rotation":10740},{"name":"Tree1","id":2575,"position":[8448,3456],"rotation":26578},{"name":"Tree1","id":2576,"position":[8320,5888],"rotation":16930},{"name":"Tree3","id":2577,"position":[6080,4416],"rotation":50426},{"name":"TreeSnow3","id":2578,"position":[4800,7616],"rotation":65171},{"name":"TreeSnow3","id":2579,"position":[4032,6464],"rotation":4369},{"name":"TreeSnow3","id":2580,"position":[8256,2496],"rotation":11468},{"name":"Tree3","id":2581,"position":[7616,1984],"rotation":36226},{"name":"Tree3","id":2584,"position":[7232,3008],"rotation":24758},{"name":"TreeSnow3","id":2585,"position":[5440,1856],"rotation":59528},{"name":"WaterTower","id":2586,"position":[4928,2880],"rotation":32768},{"name":"Tree3","id":2587,"position":[6464,4160],"rotation":30037},{"name":"Tree1","id":2588,"position":[5888,4480],"rotation":20024},{"name":"TreeSnow3","id":2589,"position":[5696,7232],"rotation":46239},{"name":"TreeSnow3","id":2590,"position":[5440,2624],"rotation":1820},{"name":"Tree1","id":2591,"position":[7936,4224],"rotation":42052},{"name":"TreeSnow3","id":2592,"position":[8000,2752],"rotation":7281},{"name":"Tree3","id":2593,"position":[6336,4032],"rotation":11286},{"name":"Tree1","id":2594,"position":[7424,3328],"rotation":35316},{"name":"OilTower","id":2595,"position":[4672,2752],"rotation":32768},{"name":"Tree3","id":2596,"position":[7744,4160],"rotation":23119},{"name":"Tree3","id":2597,"position":[1088,2496],"rotation":20024},{"name":"Tree3","id":2563,"position":[6080,5440],"rotation":4915},{"name":"Tree3","id":2599,"position":[7104,3520],"rotation":51700},{"name":"TreeSnow3","id":2600,"position":[8512,2240],"rotation":59710},{"name":"Tree1","id":2601,"position":[4992,5248],"rotation":56615},{"name":"Tree3","id":2602,"position":[7360,2496],"rotation":34588},{"name":"TreeSnow3","id":2603,"position":[8000,3264],"rotation":27306},{"name":"Tree3","id":2604,"position":[5696,4416],"rotation":44054},{"name":"Tree3","id":2605,"position":[5440,3136],"rotation":38047},{"name":"Tree1","id":2606,"position":[8064,3968],"rotation":39321},{"name":"TreeSnow3","id":2607,"position":[8512,704],"rotation":40413},{"name":"Tree3","id":2608,"position":[7104,2112],"rotation":35134},{"name":"Tree3","id":2609,"position":[5696,3264],"rotation":57526},{"name":"TreeSnow1","id":2610,"position":[8448,2432],"rotation":16384},{"name":"TreeSnow3","id":2611,"position":[7872,3008],"rotation":53339},{"name":"Tree1","id":2612,"position":[7680,768],"rotation":40960},{"name":"Tree1","id":2613,"position":[7296,3584],"rotation":21117},{"name":"TreeSnow3","id":2614,"position":[7616,3136],"rotation":51154},{"name":"Tree1","id":2615,"position":[6272,4224],"rotation":9102},{"name":"Tree3","id":2616,"position":[7744,3904],"rotation":11286},{"name":"Tree1","id":2617,"position":[7168,2304],"rotation":64079},{"name":"TreeSnow3","id":2618,"position":[5440,1728],"rotation":41688},{"name":"Tree1","id":2619,"position":[7296,1920],"rotation":45693},{"name":"OilTower","id":2620,"position":[4800,2752],"rotation":32768},{"name":"Tree1","id":2621,"position":[7168,3200],"rotation":0},{"name":"WreckedSuzukiJeep","id":2622,"position":[5184,3136],"rotation":16566},{"name":"Tree3","id":2623,"position":[7872,960],"rotation":8920},{"name":"Tree3","id":2624,"position":[8128,3776],"rotation":24211},{"name":"OilResource","id":2625,"position":[5184,7616],"rotation":32768},{"name":"WaterTower","id":2626,"position":[576,7360],"rotation":32768},{"name":"Tree1","id":2628,"position":[7680,3712],"rotation":64079},{"name":"Tree1","id":2629,"position":[8064,3584],"rotation":31311},{"name":"Tree3","id":2630,"position":[7744,1472],"rotation":36955},{"name":"TreeSnow3","id":2631,"position":[4928,2368],"rotation":22027},{"name":"TreeSnow3","id":2632,"position":[5568,2624],"rotation":29673},{"name":"TreeSnow3","id":2633,"position":[3008,5184],"rotation":44964},{"name":"OilResource","id":2513,"position":[3008,4288],"rotation":32768},{"name":"Tree3","id":2636,"position":[8512,5696],"rotation":5825},{"name":"TreeSnow3","id":2637,"position":[3136,5696],"rotation":41506},{"name":"Tree3","id":2638,"position":[6208,2240],"rotation":49698},{"name":"BarbWarehouse3","id":2639,"position":[4288,3392],"rotation":32768},{"name":"Tree3","id":2640,"position":[4928,5440],"rotation":12379},{"name":"Pickup","id":2641,"position":[4160,2880],"rotation":38957},{"name":"Tree3","id":2642,"position":[5952,2880],"rotation":31675},{"name":"BarbWarehouse3","id":2643,"position":[4160,3008],"rotation":32768},{"name":"Tree3","id":2644,"position":[5952,2368],"rotation":19296},{"name":"Tree3","id":2645,"position":[6080,2496],"rotation":11468},{"name":"Tree3","id":2646,"position":[5440,5568],"rotation":41688},{"name":"Tree3","id":2569,"position":[7488,5056],"rotation":728},{"name":"BarbWarehouse1","id":2648,"position":[4480,2752],"rotation":32768},{"name":"Tree1","id":2649,"position":[4992,1792],"rotation":28945},{"name":"Tree3","id":2690,"position":[7488,5696],"rotation":53156},{"name":"TreeSnow3","id":2651,"position":[7104,6976],"rotation":14745},{"name":"Tree3","id":2582,"position":[6720,6464],"rotation":61713},{"name":"Tree3","id":2653,"position":[5056,1600],"rotation":11832},{"name":"Tree1","id":2654,"position":[6016,1920],"rotation":46603},{"name":"Tree3","id":2655,"position":[1344,7360],"rotation":1092},{"name":"TreeSnow3","id":2656,"position":[3136,5952],"rotation":57890},{"name":"OilResource","id":2657,"position":[4544,3008],"rotation":32768},{"name":"Tree1","id":2658,"position":[5632,1280],"rotation":44418},{"name":"Tree3","id":2659,"position":[4032,3520],"rotation":4369},{"name":"BarbWarehouse1","id":2660,"position":[640,6976],"rotation":32768},{"name":"TreeSnow3","id":2661,"position":[3264,5440],"rotation":55705},{"name":"TreeSnow3","id":2650,"position":[5696,6336],"rotation":45875},{"name":"Tree3","id":2663,"position":[4672,1600],"rotation":38957},{"name":"LogCabin1","id":2665,"position":[4928,3648],"rotation":32768},{"name":"Tree3","id":2652,"position":[6976,6720],"rotation":16748},{"name":"TreeSnow1","id":2667,"position":[896,4992],"rotation":56069},{"name":"TreeSnow3","id":2668,"position":[2496,5312],"rotation":53339},{"name":"Tree3","id":2669,"position":[8000,5440],"rotation":38047},{"name":"BarbWarehouse1","id":2670,"position":[4992,3264],"rotation":32768},{"name":"WreckedVertCampVan","id":2671,"position":[4288,2752],"rotation":42780},{"name":"Tree3","id":2672,"position":[4416,4160],"rotation":27306},{"name":"OilResource","id":2635,"position":[7488,5952],"rotation":32768},{"name":"TreeSnow3","id":2674,"position":[4288,4928],"rotation":33678},{"name":"Tree3","id":2675,"position":[448,6720],"rotation":38775},{"name":"Tree3","id":2676,"position":[576,3648],"rotation":62259},{"name":"BarbWarehouse3","id":2677,"position":[1088,7360],"rotation":32768},{"name":"TreeSnow3","id":2678,"position":[5184,6208],"rotation":17840},{"name":"Tree3","id":2679,"position":[4672,5184],"rotation":25850},{"name":"Tree1","id":2662,"position":[6016,6400],"rotation":51882},{"name":"Tree3","id":2681,"position":[5952,1472],"rotation":19296},{"name":"OilResource","id":2682,"position":[3136,5568],"rotation":32768},{"name":"TreeSnow3","id":2683,"position":[5312,1984],"rotation":18750},{"name":"TreeSnow3","id":2684,"position":[4288,5312],"rotation":10194},{"name":"Tree3","id":2685,"position":[8256,5312],"rotation":60802},{"name":"OilResource","id":2686,"position":[2240,5952],"rotation":32768},{"name":"TreeSnow3","id":2687,"position":[4160,6208],"rotation":1456},{"name":"Tree3","id":2666,"position":[6208,6592],"rotation":26396},{"name":"Tree3","id":2689,"position":[4032,3264],"rotation":14017},{"name":"Tree1","id":2673,"position":[7808,5888],"rotation":59710},{"name":"Tree1","id":2691,"position":[4096,5888],"rotation":2002},{"name":"Tree3","id":2692,"position":[4288,1600],"rotation":33314},{"name":"TreeSnow3","id":2693,"position":[7360,7104],"rotation":15837},{"name":"Tree3","id":2634,"position":[2752,4672],"rotation":64443},{"name":"Tree3","id":2695,"position":[3776,2112],"rotation":1274},{"name":"Tree3","id":2696,"position":[4544,1600],"rotation":42780},{"name":"Tree3","id":2697,"position":[2880,1856],"rotation":46785},{"name":"Tree3","id":2698,"position":[2880,2112],"rotation":910},{"name":"BarbWarehouse3","id":2699,"position":[5184,3264],"rotation":32768},{"name":"Tree3","id":2700,"position":[4928,4544],"rotation":49516},{"name":"Tree3","id":2701,"position":[4800,1856],"rotation":30037},{"name":"Tree3","id":2702,"position":[2496,1472],"rotation":48605},{"name":"Tree3","id":2703,"position":[2752,1600],"rotation":44782},{"name":"Tree3","id":2704,"position":[2240,1728],"rotation":25486},{"name":"Tree3","id":2706,"position":[4416,5568],"rotation":56797},{"name":"Tree3","id":2707,"position":[6080,2752],"rotation":29491},{"name":"TreeSnow3","id":2708,"position":[8384,6592],"rotation":10376},{"name":"Tree3","id":2709,"position":[1344,1984],"rotation":28034},{"name":"OilResource","id":2710,"position":[704,7488],"rotation":32768},{"name":"TreeSnow3","id":2711,"position":[448,4416],"rotation":42780},{"name":"Tree3","id":2712,"position":[1344,1728],"rotation":32585},{"name":"TreeSnow3","id":2713,"position":[5312,2368],"rotation":8192},{"name":"Tree3","id":2715,"position":[1344,3136],"rotation":12743},{"name":"Tree3","id":2716,"position":[1600,1472],"rotation":11286},{"name":"Tree3","id":2717,"position":[1216,3264],"rotation":46967},{"name":"Tree1","id":2705,"position":[6528,5248],"rotation":47695},{"name":"Tree3","id":2719,"position":[960,4288],"rotation":42052},{"name":"Tree3","id":2720,"position":[1088,3520],"rotation":12379},{"name":"Tree3","id":2721,"position":[960,3264],"rotation":53703},{"name":"Tree3","id":2722,"position":[1856,1600],"rotation":3094},{"name":"Tree1","id":2723,"position":[3072,2176],"rotation":34406},{"name":"Tree3","id":2724,"position":[6080,3136],"rotation":48969},{"name":"Crane","id":2725,"position":[4928,3392],"rotation":13653},{"name":"Tree3","id":2726,"position":[1472,1728],"rotation":52792},{"name":"Tree3","id":2727,"position":[3392,1984],"rotation":57708},{"name":"Tree1","id":2728,"position":[3968,2176],"rotation":33132},{"name":"Tree3","id":2729,"position":[1600,2752],"rotation":51882},{"name":"Tree1","id":2730,"position":[1408,2560],"rotation":64989},{"name":"Tree3","id":2731,"position":[1088,1856],"rotation":62805},{"name":"Tree3","id":2732,"position":[4288,5824],"rotation":56979},{"name":"Tree3","id":2733,"position":[2112,1472],"rotation":20935},{"name":"TreeSnow3","id":2734,"position":[2624,5312],"rotation":39321},{"name":"Tree3","id":2714,"position":[1856,3392],"rotation":57344},{"name":"Tree3","id":2736,"position":[1984,1344],"rotation":0},{"name":"Tree3","id":2737,"position":[3904,1856],"rotation":9284},{"name":"Tree3","id":2738,"position":[4160,1984],"rotation":36590},{"name":"TreeSnow3","id":2739,"position":[5568,2496],"rotation":53521},{"name":"Tree1","id":2740,"position":[2304,1408],"rotation":39503},{"name":"Tree3","id":2742,"position":[4672,4544],"rotation":12379},{"name":"TreeSnow3","id":2743,"position":[448,5312],"rotation":4187},{"name":"Tree3","id":2741,"position":[3008,3392],"rotation":45875},{"name":"Tree3","id":2745,"position":[1216,2880],"rotation":62077},{"name":"Tree3","id":2773,"position":[2240,2880],"rotation":60074},{"name":"Tree3","id":2747,"position":[1216,2240],"rotation":4551},{"name":"Tree3","id":2748,"position":[4288,1856],"rotation":58436},{"name":"Tree3","id":2749,"position":[3008,1856],"rotation":25668},{"name":"Tree1","id":2750,"position":[4480,6016],"rotation":48423},{"name":"Tree1","id":2751,"position":[5376,2944],"rotation":28580},{"name":"TreeSnow3","id":2752,"position":[1984,2496],"rotation":27124},{"name":"Crane","id":2753,"position":[576,7616],"rotation":54431},{"name":"TreeSnow1","id":2754,"position":[1792,5248],"rotation":23847},{"name":"Tree3","id":2767,"position":[3264,4160],"rotation":24029},{"name":"Tree3","id":2756,"position":[960,3520],"rotation":23301},{"name":"LogCabin1","id":2757,"position":[5056,3648],"rotation":32768},{"name":"TreeSnow3","id":2664,"position":[1728,4672],"rotation":31311},{"name":"Tree3","id":2759,"position":[704,3648],"rotation":55705},{"name":"Tree3","id":2760,"position":[576,4032],"rotation":16566},{"name":"Tree3","id":2761,"position":[5312,1472],"rotation":17112},{"name":"Tree3","id":2762,"position":[8256,5696],"rotation":12014},{"name":"TreeSnow3","id":2763,"position":[1728,2112],"rotation":55705},{"name":"Tree3","id":2694,"position":[2880,4416],"rotation":39867},{"name":"OilTower","id":2765,"position":[576,7104],"rotation":32768},{"name":"BarbWarehouse1","id":2766,"position":[768,7616],"rotation":32768},{"name":"TreeSnow3","id":2768,"position":[5312,1856],"rotation":28398},{"name":"Tree3","id":2769,"position":[1216,4032],"rotation":11468},{"name":"TreeSnow3","id":2770,"position":[4160,2496],"rotation":33860},{"name":"Tree3","id":2647,"position":[7616,5056],"rotation":18932},{"name":"TreeSnow3","id":2772,"position":[2368,2112],"rotation":30765},{"name":"OilResource","id":2744,"position":[3008,3648],"rotation":32768},{"name":"Tree3","id":2774,"position":[832,3904],"rotation":47513},{"name":"TreeSnow3","id":2775,"position":[3520,2880],"rotation":3822},{"name":"TreeSnow3","id":2776,"position":[1472,3520],"rotation":5097},{"name":"Tree3","id":2777,"position":[5952,1728],"rotation":52064},{"name":"Tree3","id":2778,"position":[5952,2112],"rotation":44782},{"name":"Tree3","id":2779,"position":[5056,4928],"rotation":64807},{"name":"Tree1","id":2780,"position":[512,3840],"rotation":3640},{"name":"TreeSnow3","id":2781,"position":[5696,2880],"rotation":2912},{"name":"TreeSnow3","id":2782,"position":[3648,2368],"rotation":43872},{"name":"TreeSnow3","id":2783,"position":[1344,3520],"rotation":31857},{"name":"Tree1","id":2627,"position":[7552,6528],"rotation":42962},{"name":"Tree3","id":2735,"position":[1600,3776],"rotation":26214},{"name":"TreeSnow3","id":2786,"position":[1344,3648],"rotation":56797},{"name":"TreeSnow3","id":2787,"position":[2496,2368],"rotation":20935},{"name":"BarbWarehouse2","id":2788,"position":[4096,3392],"rotation":32768},{"name":"TreeSnow3","id":2789,"position":[3520,3520],"rotation":52610},{"name":"TreeSnow3","id":2790,"position":[1344,3776],"rotation":55887},{"name":"TreeSnow3","id":2791,"position":[3648,2752],"rotation":45875},{"name":"Tree3","id":2792,"position":[4672,6080],"rotation":23483},{"name":"TreeSnow3","id":2793,"position":[3520,3264],"rotation":35134},{"name":"TreeSnow3","id":2794,"position":[3520,3392],"rotation":54431},{"name":"Tree1","id":2598,"position":[5632,5888],"rotation":26760},{"name":"TreeSnow3","id":2796,"position":[1856,1856],"rotation":28580},{"name":"Tree1","id":2718,"position":[6272,5504],"rotation":5825},{"name":"Tree3","id":2798,"position":[5056,1344],"rotation":59164},{"name":"Tree3","id":2799,"position":[4672,4288],"rotation":41688},{"name":"Tree3","id":2800,"position":[4544,4544],"rotation":24940},{"name":"Tree3","id":2801,"position":[5824,1984],"rotation":4733},{"name":"TreeSnow3","id":2802,"position":[5696,2496],"rotation":32950},{"name":"TreeSnow3","id":2803,"position":[8000,6336],"rotation":38047},{"name":"Tree1","id":2688,"position":[6784,6656],"rotation":50426},{"name":"OilResource","id":2804,"position":[7104,6592],"rotation":32768},{"name":"Tree1","id":2764,"position":[3072,4480],"rotation":0}]}